control_lyapunov/__init__.py
control_lyapunov/learning.py
control_lyapunov/simulation.py
control_lyapunov/sontag.py
control_lyapunov/utils.py
control_lyapunov/verification.py
control_lyapunov/models/__init__.py
control_lyapunov/models/inverted_pendulum.py
control_lyapunov/models/van_der_pol.py
control_lyapunov-0.1.0.dist-info/licenses/LICENSE
examples/__init__.py
examples/van_der_pol_example.py
control_lyapunov-0.1.0.dist-info/METADATA
control_lyapunov-0.1.0.dist-info/WHEEL
control_lyapunov-0.1.0.dist-info/top_level.txt
control_lyapunov-0.1.0.dist-info/RECORD
