Metadata-Version: 2.4
Name: control-lyapunov
Version: 0.1.0
Summary: A data-driven framework for synthesizing feedback controllers using learned Control Lyapunov Functions
Home-page: https://github.com/Vrushabh27/control-lyapunov
Author: Vrushabh Zinage, Shrenik Zinage
Author-email: Vrushabh Zinage <vrushabh@example.com>, Shrenik Zinage <shrenik@example.com>
License: MIT
Project-URL: Homepage, https://github.com/Vrushabh27/control-lyapunov
Project-URL: Bug Tracker, https://github.com/Vrushabh27/control-lyapunov/issues
Project-URL: Documentation, https://github.com/Vrushabh27/control-lyapunov
Keywords: control theory,lyapunov,machine learning,nonlinear systems,verification
Classifier: Programming Language :: Python :: 3
Classifier: Programming Language :: Python :: 3.7
Classifier: Programming Language :: Python :: 3.8
Classifier: Programming Language :: Python :: 3.9
Classifier: License :: OSI Approved :: MIT License
Classifier: Operating System :: OS Independent
Classifier: Topic :: Scientific/Engineering :: Artificial Intelligence
Classifier: Topic :: Scientific/Engineering :: Mathematics
Requires-Python: >=3.7
License-File: LICENSE
Requires-Dist: torch>=1.8.0
Requires-Dist: numpy>=1.19.0
Requires-Dist: scipy>=1.6.0
Requires-Dist: sympy>=1.7.0
Requires-Dist: matplotlib>=3.3.0
Dynamic: author
Dynamic: home-page
Dynamic: license-file
Dynamic: requires-python
